{
    "modelParams": {
        "hidden_size": 192,
        "num_layers": 1,
        "dropout": 0.500786843271666,
        "num_filters": 24,
        "kernel_size": 7
    },
    "lookback": 20,
    "allParams": {
        "hidden_size": 192,
        "num_layers": 1,
        "dropout": 0.5,
        "lookback": 20,
        "optimiser": "RMSprop",
        "lr": 7e-4,
        "weight_decay": 6e-05,
        "batch_size": 192,
        "clip_grad_norm": 4.87,
        "num_filters": 24,
        "kernel_size": 7
    }
}